bmt/__init__.py
bmt/data.py
bmt/util.py
bmt/_data/__init__.py
bmt/_data/alias_ancestors.json
bmt/_data/alias_children.json
bmt/_data/alias_descendants.json
bmt/_data/alias_mixin_ancestors.json
bmt/_data/alias_mixin_children.json
bmt/_data/alias_mixin_descendants.json
bmt/_data/all_classes.json
bmt/_data/all_elements.json
bmt/_data/all_slots.json
bmt/_data/all_types.json
bmt/_data/basic_ancestors.json
bmt/_data/basic_children.json
bmt/_data/basic_descendants.json
bmt/_data/element.json
bmt/_data/mixin_ancestors.json
bmt/_data/mixin_children.json
bmt/_data/mixin_descendants.json
bmt/_data/parent.json
bmt_lite_1.7.0-2.2.0.dist-info/LICENSE
bmt_lite_1.7.0-2.2.0.dist-info/METADATA
bmt_lite_1.7.0-2.2.0.dist-info/WHEEL
bmt_lite_1.7.0-2.2.0.dist-info/top_level.txt
bmt_lite_1.7.0-2.2.0.dist-info/RECORD
